{"type":"blinky-mqtt","name":"picoW-01","arcPeriod":60000,"timeStamp":1708443456289,"watchdog":{"action":"reading","type":"scalar","value":25,"unit":"","alarm":{"value":0,"limits":{"lolo":-1,"low":0,"high":70000,"hihi":80000},"notify":{"name":"","number":"","time":0}},"blinkybus":{"address":1,"scale":1}},"led1":{"action":"setting","type":"scalar","unit":"","alarm":{"value":0,"limits":{"lolo":-1,"low":-1,"high":256,"hihi":256},"notify":{"name":"","number":"","time":0}},"value":240,"blinkybus":{"address":3,"scale":1}},"led2":{"action":"setting","type":"scalar","unit":"","alarm":{"value":0,"limits":{"lolo":-1,"low":-1,"high":256,"hihi":256},"notify":{"name":"","number":"","time":0}},"value":90,"blinkybus":{"address":4,"scale":1}},"chipTemp":{"action":"reading","type":"scalar","value":24.79,"unit":"C","alarm":{"value":0,"limits":{"lolo":8,"low":9,"high":40,"hihi":45},"notify":{"name":"My Test Group","number":"-4045978710","time":0}},"blinkybus":{"address":2,"scale":100}},"crv":{"action":"setting","type":"vector","value":[[1.56421,1.5677,1.66675,1.76422,1.95477,2.08934,2.21181,2.27933,2.3135,2.34153,2.37325,2.4114,2.43315,2.4577,2.48661,2.52299,2.56517,2.57476,2.58027,2.58539,2.59095,2.59688,2.6026,2.60855,2.61514,2.62072,2.6421,2.6492,2.69967,2.73023,2.7811,2.82582,2.84413,2.86233,2.88272,2.88315,2.92893,2.94182,2.95578,3.01467],[295.639,292.149,210.81,152.955,77.3594,45.316,26.4051,19.1127,16.1483,14.0532,11.9996,9.97317,8.99769,8.00747,7.02038,5.97645,5.00227,4.80644,4.70223,4.60093,4.50333,4.40072,4.30269,4.1998,4.09878,4.00796,3.69795,3.60391,3.00121,2.70425,2.29261,1.99981,1.89427,1.79737,1.69804,1.69522,1.49999,1.44947,1.4006,1.21335]]},"alias":{"action":"setting","type":"string","value":"picoW 01"},"trayControl":{"action":"setting","type":"scalar","value":0,"unit":"","alarm":{"value":0,"limits":{"lolo":-1,"low":-1,"high":1,"hihi":1},"notify":{"name":"","number":"","time":0}}}}
{"type":"blinky-mqtt","name":"admin","arcPeriod":60000,"timeStamp":1684397726547,"alias":{"action":"setting","type":"string","value":"admin"},"reloadTrays":{"action":"setting","type":"scalar","unit":"","alarm":{"value":0,"limits":{"lolo":-1,"low":-1,"high":2,"hihi":2},"notify":{"name":"","number":"","time":0}},"value":0}}

